kostalpiko/__init__.py
kostalpiko/const.py
kostalpiko/kostalpiko.py
kostalpiko/utils.py
tests/__init__.py
tests/test_kostalpiko_2_1.py
tests/test_kostalpiko_5_5_1.py
tests/test_kostalpiko_5_5_2.py
kostalpiko-0.6.dist-info/LICENSE.txt
kostalpiko-0.6.dist-info/METADATA
kostalpiko-0.6.dist-info/WHEEL
kostalpiko-0.6.dist-info/top_level.txt
kostalpiko-0.6.dist-info/RECORD
