Metadata-Version: 2.1
Name: kostalpiko
Version: 0.6
Summary: A package for working with a Piko Inverter from Kostal
Home-page: https://github.com/rcasula/kostalpiko
Author: Roberto Casula
Author-email: roberto@casula.dev
License: MIT
License-File: LICENSE.txt
Requires-Dist: lxml
